mesh/__init__.py
mesh/auth.py
mesh/auth_cli.py
mesh/auto_refresh_client.py
mesh/client.py
mesh/config.py
mesh/models.py
mesh/token_manager.py
mesh/zkp_client.py
mesh_beta-1.0.3.dist-info/METADATA
mesh_beta-1.0.3.dist-info/WHEEL
mesh_beta-1.0.3.dist-info/entry_points.txt
mesh_beta-1.0.3.dist-info/top_level.txt
mesh_beta-1.0.3.dist-info/RECORD
