Metadata-Version: 2.2
Name: mesh-beta
Version: 1.0.3
Summary: Official Python SDK for the Mesh API - Secure key management and AI model access
Home-page: https://github.com/meshsdk/mesh-python
Author: Mesh Team
Author-email: support@meshsdk.io
Project-URL: Documentation, https://docs.meshsdk.io
Project-URL: Source, https://github.com/meshsdk/mesh-python
Project-URL: Issues, https://github.com/meshsdk/mesh-python/issues
Keywords: mesh,api,sdk,security,key management,zero knowledge proofs,ai,openai,anthropic
Classifier: Development Status :: 5 - Production/Stable
Classifier: Intended Audience :: Developers
Classifier: License :: OSI Approved :: MIT License
Classifier: Operating System :: OS Independent
Classifier: Programming Language :: Python :: 3
Classifier: Programming Language :: Python :: 3.7
Classifier: Programming Language :: Python :: 3.8
Classifier: Programming Language :: Python :: 3.9
Classifier: Programming Language :: Python :: 3.10
Classifier: Programming Language :: Python :: 3.11
Classifier: Topic :: Security
Classifier: Topic :: Software Development :: Libraries :: Python Modules
Requires-Python: >=3.7
Requires-Dist: requests>=2.31.0
Requires-Dist: keyring>=24.3.0
Requires-Dist: cryptography>=42.0.0
Requires-Dist: pyjwt>=2.8.0
Requires-Dist: urllib3>=2.0.0
Requires-Dist: certifi>=2024.2.0
Provides-Extra: dev
Requires-Dist: pytest>=7.0.0; extra == "dev"
Requires-Dist: pytest-cov>=4.0.0; extra == "dev"
Requires-Dist: black>=24.0.0; extra == "dev"
Requires-Dist: isort>=5.13.0; extra == "dev"
Requires-Dist: mypy>=1.8.0; extra == "dev"
Requires-Dist: types-requests>=2.31.0; extra == "dev"
Requires-Dist: types-urllib3>=1.26.25; extra == "dev"
Provides-Extra: docs
Requires-Dist: sphinx>=7.0.0; extra == "docs"
Requires-Dist: sphinx-rtd-theme>=2.0.0; extra == "docs"
Dynamic: author
Dynamic: author-email
Dynamic: classifier
Dynamic: description
Dynamic: description-content-type
Dynamic: home-page
Dynamic: keywords
Dynamic: project-url
Dynamic: provides-extra
Dynamic: requires-dist
Dynamic: requires-python
Dynamic: summary
